pdf_string_search/__init__.py
pdf_string_search/main.py
pdf_string_search-0.1.0.dist-info/LICENSE
pdf_string_search-0.1.0.dist-info/METADATA
pdf_string_search-0.1.0.dist-info/WHEEL
pdf_string_search-0.1.0.dist-info/entry_points.txt
pdf_string_search-0.1.0.dist-info/top_level.txt
pdf_string_search-0.1.0.dist-info/RECORD
